omnibase_spi/__init__.py
omnibase_spi/__init__.py.lazy
omnibase_spi/contracts/__init__.py
omnibase_spi/contracts/defaults/__init__.py
omnibase_spi/contracts/defaults/default_compute_handler.yaml
omnibase_spi/contracts/defaults/default_effect_handler.yaml
omnibase_spi/contracts/defaults/default_nondeterministic_compute_handler.yaml
omnibase_spi/exceptions.py
omnibase_spi/factories/__init__.py
omnibase_spi/protocols/README.md
omnibase_spi/protocols/__init__.py
omnibase_spi/protocols/advanced/__init__.py
omnibase_spi/protocols/advanced/protocol_adaptive_chunker.py
omnibase_spi/protocols/advanced/protocol_ast_builder.py
omnibase_spi/protocols/advanced/protocol_contract_analyzer.py
omnibase_spi/protocols/advanced/protocol_coverage_provider.py
omnibase_spi/protocols/advanced/protocol_direct_knowledge_pipeline.py
omnibase_spi/protocols/advanced/protocol_enum_generator.py
omnibase_spi/protocols/advanced/protocol_fixture_loader.py
omnibase_spi/protocols/advanced/protocol_log_format_handler.py
omnibase_spi/protocols/advanced/protocol_multi_vector_indexer.py
omnibase_spi/protocols/advanced/protocol_orchestrator.py
omnibase_spi/protocols/advanced/protocol_output_field_tool.py
omnibase_spi/protocols/advanced/protocol_output_formatter.py
omnibase_spi/protocols/advanced/protocol_stamper.py
omnibase_spi/protocols/advanced/protocol_stamper_engine.py
omnibase_spi/protocols/analytics/__init__.py
omnibase_spi/protocols/analytics/protocol_analytics_provider.py
omnibase_spi/protocols/cli/__init__.py
omnibase_spi/protocols/cli/protocol_cli.py
omnibase_spi/protocols/cli/protocol_cli_dir_fixture_case.py
omnibase_spi/protocols/cli/protocol_cli_dir_fixture_registry.py
omnibase_spi/protocols/cli/protocol_cli_tool_discovery.py
omnibase_spi/protocols/cli/protocol_cli_workflow.py
omnibase_spi/protocols/cli/protocol_node_cli_adapter.py
omnibase_spi/protocols/container/__init__.py
omnibase_spi/protocols/container/protocol_artifact_container.py
omnibase_spi-0.6.4.dist-info/METADATA
omnibase_spi-0.6.4.dist-info/WHEEL
omnibase_spi-0.6.4.dist-info/licenses/LICENSE
omnibase_spi-0.6.4.dist-info/RECORD
