Metadata-Version: 2.4
Name: omnibase_spi
Version: 0.6.4
Summary: ONEX Service Provider Interface - Protocol definitions
License: MIT
License-File: LICENSE
Author: OmniNode Team
Author-email: team@omninode.ai
Requires-Python: >=3.12
Classifier: Development Status :: 4 - Beta
Classifier: Intended Audience :: Developers
Classifier: License :: OSI Approved :: MIT License
Classifier: Programming Language :: Python :: 3
Classifier: Programming Language :: Python :: 3.12
Classifier: Topic :: Software Development :: Libraries :: Python Modules
Classifier: Typing :: Typed
Requires-Dist: omnibase-core (>=0.9.11)
Requires-Dist: pydantic (>=2.11.7)
Requires-Dist: typing-extensions (>=4.5.0)
